README.rst
setup.cfg
setup.py
switchy/__init__.py
switchy/cli.py
switchy/commands.py
switchy/connection.py
switchy/distribute.py
switchy/marks.py
switchy/models.py
switchy/observe.py
switchy/serve.py
switchy/sync.py
switchy/utils.py
switchy/xreload.py
switchy.egg-info/PKG-INFO
switchy.egg-info/SOURCES.txt
switchy.egg-info/dependency_links.txt
switchy.egg-info/entry_points.txt
switchy.egg-info/requires.txt
switchy.egg-info/top_level.txt
switchy/../conf/switchydp.xml
switchy/apps/__init__.py
switchy/apps/bert.py
switchy/apps/blockers.py
switchy/apps/call_gen.py
switchy/apps/dtmf.py
switchy/apps/players.py
switchy/apps/routers.py
switchy/apps/measure/__init__.py
switchy/apps/measure/cdr.py
switchy/apps/measure/mpl_helpers.py
switchy/apps/measure/shmarray.py
switchy/apps/measure/storage.py
switchy/apps/measure/sys.py