Metadata-Version: 1.1
Name: switchy
Version: 0.1.0a1
Summary: A fast FreeSWITCH control library purpose-built on traffic theory and stress testing.
Home-page: https://github.com/sangoma/switchy
Author: Tyler Goodlet
Author-email: tgoodlet@sangoma.com
License: Mozilla
Platform: linux
Classifier: Development Status :: 3 - Alpha
Classifier: License :: OSI Approved :: Mozilla Public License 2.0 (MPL 2.0)
Classifier: Operating System :: POSIX :: Linux
Classifier: Programming Language :: Python :: 2.7
Classifier: Programming Language :: Python :: 3.5
Classifier: Intended Audience :: Telecommunications Industry
Classifier: Intended Audience :: Developers
Classifier: Topic :: Communications :: Telephony
Classifier: Topic :: Software Development :: Testing :: Traffic Generation
Classifier: Topic :: System :: Clustering
Classifier: Environment :: Console
